{"_type":"export","__export_format":4,"__export_date":"2019-09-09T15:12:37.949Z","__export_source":"insomnia.desktop.app:v6.6.2","resources":[{"_id":"req_0f95b44e929e4601994fd3a5939d9ef3","authentication":{},"body":{},"created":1566444086286,"description":"","headers":[],"isPrivate":false,"metaSortKey":-1566445030982,"method":"GET","modified":1566445080581,"name":"Listar ","parameters":[],"parentId":"wrk_a3fd4943cc3b48818865f7b3823b2f0d","settingDisableRenderRequestBody":false,"settingEncodeUrl":true,"settingRebuildPath":true,"settingSendCookies":true,"settingStoreCookies":true,"url":"localhost:3000/projects","_type":"request"},{"_id":"wrk_a3fd4943cc3b48818865f7b3823b2f0d","created":1566359430858,"description":"","modified":1566359430858,"name":"Insomnia","parentId":null,"_type":"workspace"},{"_id":"req_b73e697e7c124d928330a3fc30f0262c","authentication":{},"body":{"mimeType":"application/json","text":"{\n\t\"id\": \"4\",\n\t\"title\": \"Novo projeto\"\n}"},"created":1566444109636,"description":"","headers":[{"disabled":false,"id":"pair_0fc24d3d16d64cee8a49e0397ef0990b","name":"Content-Type","value":"application/json"},{"disabled":true,"id":"pair_8ad6f7556b1a4a7aa91a3c8f5a11ea55","name":"","value":""}],"isPrivate":false,"metaSortKey":-1566445030957,"method":"POST","modified":1566446450642,"name":"Criar project","parameters":[],"parentId":"wrk_a3fd4943cc3b48818865f7b3823b2f0d","settingDisableRenderRequestBody":false,"settingEncodeUrl":true,"settingRebuildPath":true,"settingSendCookies":true,"settingStoreCookies":true,"url":"localhost:3000/projects","_type":"request"},{"_id":"req_83690952a45846f782a5686ddd9fd9c4","authentication":{},"body":{"mimeType":"application/json","text":"{\n\t\"title\": \"node é bom\"\n}"},"created":1566444390884,"description":"","headers":[{"id":"pair_61262550f82d43e29cbf712a72c7b4fd","name":"Content-Type","value":"application/json"}],"isPrivate":false,"metaSortKey":-1566444390884,"method":"PUT","modified":1566444415124,"name":"Editar title","parameters":[],"parentId":"wrk_a3fd4943cc3b48818865f7b3823b2f0d","settingDisableRenderRequestBody":false,"settingEncodeUrl":true,"settingRebuildPath":true,"settingSendCookies":true,"settingStoreCookies":true,"url":"localhost:3000/projects/2","_type":"request"},{"_id":"req_23bcd14faa1c48c78fe5610c9e39d429","authentication":{},"body":{},"created":1566444733060,"description":"","headers":[],"isPrivate":false,"metaSortKey":-1566444390834,"method":"DELETE","modified":1566445460818,"name":"Deletar ","parameters":[],"parentId":"wrk_a3fd4943cc3b48818865f7b3823b2f0d","settingDisableRenderRequestBody":false,"settingEncodeUrl":true,"settingRebuildPath":true,"settingSendCookies":true,"settingStoreCookies":true,"url":"localhost:3000/projects/5","_type":"request"},{"_id":"req_8c3146374f1049d38e5816673c0576e9","authentication":{},"body":{"mimeType":"application/json","text":"{\n\t\"title\": \"node é bom\"\n}"},"created":1566445030932,"description":"","headers":[{"id":"pair_0e77bf73e9a7499ebc2ea21938f26d39","name":"Content-Type","value":"application/json"}],"isPrivate":false,"metaSortKey":-1566445030932,"method":"POST","modified":1566446457421,"name":"Cadastras task","parameters":[],"parentId":"wrk_a3fd4943cc3b48818865f7b3823b2f0d","settingDisableRenderRequestBody":false,"settingEncodeUrl":true,"settingRebuildPath":true,"settingSendCookies":true,"settingStoreCookies":true,"url":"localhost:3000/projects/2/tasks","_type":"request"},{"_id":"req_4feb8328d724442a8f7943906b09c419","authentication":{},"body":{"mimeType":"application/json","text":"{\n\t\"name\": \"Jadiê Oliveira\",\n\t\"email\": \"jadietest4@gmail.com\",\n\t\"password\": \"123456\",\n\t\"provider\": true\n}"},"created":1567085352093,"description":"","headers":[{"id":"pair_8d14c5a10b4a42b2a3c2de4aa8f5599e","name":"Content-Type","value":"application/json"}],"isPrivate":false,"metaSortKey":-1567463999905,"method":"POST","modified":1567815426212,"name":"Create","parameters":[],"parentId":"fld_dfba14769bb746739300b91be685e1d7","settingDisableRenderRequestBody":false,"settingEncodeUrl":true,"settingRebuildPath":true,"settingSendCookies":true,"settingStoreCookies":true,"url":"{{ base_url  }}/users","_type":"request"},{"_id":"fld_dfba14769bb746739300b91be685e1d7","created":1567463999954,"description":"","environment":{},"environmentPropertyOrder":null,"metaSortKey":-1567463999955,"modified":1567463999954,"name":"User","parentId":"wrk_b2cc40fce1ca4c6fa36186cebf570c60","_type":"request_group"},{"_id":"wrk_b2cc40fce1ca4c6fa36186cebf570c60","created":1567085270297,"description":"","modified":1567796515513,"name":"Gobarber","parentId":null,"_type":"workspace"},{"_id":"req_f34dc78e92d745ccac2e93a1fb35d156","authentication":{"token":"{{ token  }}","type":"bearer"},"body":{"mimeType":"application/json","text":"{\n\t\"name\": \"Jadiê Oliveira\",\n\t\"email\": \"jadietest3@gmail.com\",\n\t\"oldPassword\": \"123456\",\n\t\"password\": \"123456\",\n\t\"confirmPassword\": \"123456\",\n\t\"avatar_id\": \"1\"\n}"},"created":1567465113568,"description":"","headers":[{"id":"pair_8d14c5a10b4a42b2a3c2de4aa8f5599e","name":"Content-Type","value":"application/json"}],"isPrivate":false,"metaSortKey":-1566954515443.5,"method":"PUT","modified":1567775883667,"name":"Update","parameters":[],"parentId":"fld_dfba14769bb746739300b91be685e1d7","settingDisableRenderRequestBody":false,"settingEncodeUrl":true,"settingRebuildPath":true,"settingSendCookies":true,"settingStoreCookies":true,"url":"{{ base_url  }}/users","_type":"request"},{"_id":"req_7449f92b136d4ef597721dd38d4b6bbd","authentication":{},"body":{"mimeType":"application/json","text":"{\n\t\"email\": \"jadietest3@gmail.com\",\n\t\"password\": \"123456\"\n}"},"created":1567464018451,"description":"","headers":[{"id":"pair_8d14c5a10b4a42b2a3c2de4aa8f5599e","name":"Content-Type","value":"application/json"}],"isPrivate":false,"metaSortKey":-1567464005242.5,"method":"POST","modified":1567815562674,"name":"Create","parameters":[],"parentId":"fld_ff4b411982ad4d06bda07ddaf85b618a","settingDisableRenderRequestBody":false,"settingEncodeUrl":true,"settingRebuildPath":true,"settingSendCookies":true,"settingStoreCookies":true,"url":"{{ base_url  }}/sessions","_type":"request"},{"_id":"fld_ff4b411982ad4d06bda07ddaf85b618a","created":1567464010530,"description":"","environment":{},"environmentPropertyOrder":null,"metaSortKey":-1567529449622.5,"modified":1567779716459,"name":"Session","parentId":"wrk_b2cc40fce1ca4c6fa36186cebf570c60","_type":"request_group"},{"_id":"req_2fce77060b1f487f91d2da4932d4159c","authentication":{"token":"{{ token  }}","type":"bearer"},"body":{"mimeType":"multipart/form-data","params":[{"fileName":"C:\\Users\\arievilo\\Downloads\\img\\eu.jpg","id":"pair_a02f5f097e51427b9cae8e2b4eb4c105","name":"file","type":"file","value":""}]},"created":1567594902573,"description":"","headers":[{"id":"pair_ec3a69135cd34b26a694388944ea9df3","name":"Content-Type","value":"multipart/form-data"}],"isPrivate":false,"metaSortKey":-1567594902573,"method":"POST","modified":1567609238221,"name":"Create","parameters":[],"parentId":"fld_66e35e8ebeaf40be920262586fd1118c","settingDisableRenderRequestBody":false,"settingEncodeUrl":true,"settingRebuildPath":true,"settingSendCookies":true,"settingStoreCookies":true,"url":"{{ base_url  }}/files","_type":"request"},{"_id":"fld_66e35e8ebeaf40be920262586fd1118c","created":1567594888715,"description":"","environment":{},"environmentPropertyOrder":null,"metaSortKey":-1567594888715,"modified":1567594888715,"name":"File","parentId":"wrk_b2cc40fce1ca4c6fa36186cebf570c60","_type":"request_group"},{"_id":"req_c1259611cc23493e937e2cd52fd1cdd3","authentication":{"token":"{{ token  }}","type":"bearer"},"body":{},"created":1567618277548,"description":"","headers":[],"isPrivate":false,"metaSortKey":-1567618277548,"method":"GET","modified":1567618303893,"name":"index","parameters":[],"parentId":"fld_a37c7d62a490453aa77617365796e98b","settingDisableRenderRequestBody":false,"settingEncodeUrl":true,"settingRebuildPath":true,"settingSendCookies":true,"settingStoreCookies":true,"url":"{{ base_url  }}/providers","_type":"request"},{"_id":"fld_a37c7d62a490453aa77617365796e98b","created":1567618262134,"description":"","environment":{},"environmentPropertyOrder":null,"metaSortKey":-1567618262134,"modified":1567618262134,"name":"Providers","parentId":"wrk_b2cc40fce1ca4c6fa36186cebf570c60","_type":"request_group"},{"_id":"req_f581a6efc43d4a9e8293ad6139078fc5","authentication":{"token":"{{ token  }}","type":"bearer"},"body":{"mimeType":"application/json","text":"{\n\t\"provider_id\": 15,\n\t\"date\": \"2019-09-15T18:00:00-03:00\"\n}"},"created":1567771741162,"description":"","headers":[{"id":"pair_ad304c37fbe54e09961f90c640191847","name":"Content-Type","value":"application/json"}],"isPrivate":false,"metaSortKey":-1567771741162,"method":"POST","modified":1568029296297,"name":"Create","parameters":[],"parentId":"fld_0fb0c3f512cc4c919bfa9cff6dd6311a","settingDisableRenderRequestBody":false,"settingEncodeUrl":true,"settingRebuildPath":true,"settingSendCookies":true,"settingStoreCookies":true,"url":"{{ base_url  }}/appointments","_type":"request"},{"_id":"fld_0fb0c3f512cc4c919bfa9cff6dd6311a","created":1567771704106,"description":"","environment":{},"environmentPropertyOrder":null,"metaSortKey":-1567771704106,"modified":1567771704106,"name":"Appointments","parentId":"wrk_b2cc40fce1ca4c6fa36186cebf570c60","_type":"request_group"},{"_id":"req_92af6c46c6b547cfb6878cf3a5efa34b","authentication":{"token":"{{ token  }}","type":"bearer"},"body":{},"created":1567779706115,"description":"","headers":[],"isPrivate":false,"metaSortKey":-1567771741212,"method":"GET","modified":1567814965299,"name":"List","parameters":[{"id":"pair_1ed1ac6d11964bfb881d55d01963a2c3","name":"page","value":"1"}],"parentId":"fld_0fb0c3f512cc4c919bfa9cff6dd6311a","settingDisableRenderRequestBody":false,"settingEncodeUrl":true,"settingRebuildPath":true,"settingSendCookies":true,"settingStoreCookies":true,"url":"{{ base_url  }}/appointments","_type":"request"},{"_id":"req_51b659baec7a4042a65b56da25aaac5a","authentication":{"token":"{{ token  }}","type":"bearer"},"body":{},"created":1568029114424,"description":"","headers":[],"isPrivate":false,"metaSortKey":-1567695009355,"method":"DELETE","modified":1568041228871,"name":"Delete","parameters":[],"parentId":"fld_0fb0c3f512cc4c919bfa9cff6dd6311a","settingDisableRenderRequestBody":false,"settingEncodeUrl":true,"settingRebuildPath":true,"settingSendCookies":true,"settingStoreCookies":true,"url":"{{ base_url  }}/appointments/17","_type":"request"},{"_id":"req_186de849481940bb9e4c9f3414bb2890","authentication":{"token":"{{ token  }}","type":"bearer"},"body":{},"created":1567794755746,"description":"","headers":[],"isPrivate":false,"metaSortKey":-1567794755746,"method":"GET","modified":1567796350481,"name":"List","parameters":[{"id":"pair_ea13ef95955040c8aaad4b3dc48cc716","name":"date","value":"2019-09-10T00:00:00-03:00"}],"parentId":"fld_38dafa1ffc124a27a954e1d3a06510d0","settingDisableRenderRequestBody":false,"settingEncodeUrl":true,"settingRebuildPath":true,"settingSendCookies":true,"settingStoreCookies":true,"url":"{{ base_url  }}/schedule","_type":"request"},{"_id":"fld_38dafa1ffc124a27a954e1d3a06510d0","created":1567794730580,"description":"","environment":{},"environmentPropertyOrder":null,"metaSortKey":-1567794730580,"modified":1567794730580,"name":"Schedule","parentId":"wrk_b2cc40fce1ca4c6fa36186cebf570c60","_type":"request_group"},{"_id":"req_5fe17daedc344a339e7dd63115929ddd","authentication":{"token":"{{ token  }}","type":"bearer"},"body":{},"created":1567814176535,"description":"","headers":[],"isPrivate":false,"metaSortKey":-1567814176535,"method":"GET","modified":1567814201212,"name":"List","parameters":[],"parentId":"fld_abf7d9e14ecf409bbd1a054d17949d4f","settingDisableRenderRequestBody":false,"settingEncodeUrl":true,"settingRebuildPath":true,"settingSendCookies":true,"settingStoreCookies":true,"url":"{{ base_url  }}/notifications","_type":"request"},{"_id":"fld_abf7d9e14ecf409bbd1a054d17949d4f","created":1567814168374,"description":"","environment":{},"environmentPropertyOrder":null,"metaSortKey":-1567814168374,"modified":1567814168374,"name":"Notification","parentId":"wrk_b2cc40fce1ca4c6fa36186cebf570c60","_type":"request_group"},{"_id":"req_4c1412cf33f149f2a420a6f14b2be557","authentication":{"token":"{{ token  }}","type":"bearer"},"body":{},"created":1567816057854,"description":"","headers":[],"isPrivate":false,"metaSortKey":-1567804466140.5,"method":"PUT","modified":1567816076396,"name":"Update","parameters":[],"parentId":"fld_abf7d9e14ecf409bbd1a054d17949d4f","settingDisableRenderRequestBody":false,"settingEncodeUrl":true,"settingRebuildPath":true,"settingSendCookies":true,"settingStoreCookies":true,"url":"{{ base_url  }}/notifications/5d72f7becd43b71900bade9a","_type":"request"},{"_id":"env_e637150a5286d4b3a8ca7509aa794326c6a74896","color":null,"created":1566359430897,"data":{},"dataPropertyOrder":null,"isPrivate":false,"metaSortKey":1566359430897,"modified":1566359430897,"name":"Base Environment","parentId":"wrk_a3fd4943cc3b48818865f7b3823b2f0d","_type":"environment"},{"_id":"jar_e637150a5286d4b3a8ca7509aa794326c6a74896","cookies":[],"created":1566359430900,"modified":1566359430900,"name":"Default Jar","parentId":"wrk_a3fd4943cc3b48818865f7b3823b2f0d","_type":"cookie_jar"},{"_id":"env_5ec9e503e3e1b8c951c7488677600f7b0b0bb823","color":null,"created":1567085270328,"data":{"base_url":"http://localhost:3000","token":"eyJhbGciOiJIUzI1NiIsInR5cCI6IkpXVCJ9.eyJpZCI6MTUsImlhdCI6MTU2Nzc5NDk3MiwiZXhwIjoxNTY4Mzk5NzcyfQ.yDOoCNdu1jaYIo2xn8OFkL8Ozgx8Nkq_hkjq-bfOdAc"},"dataPropertyOrder":{"&":["base_url","token"]},"isPrivate":false,"metaSortKey":1567085270328,"modified":1567795029111,"name":"Base Environment","parentId":"wrk_b2cc40fce1ca4c6fa36186cebf570c60","_type":"environment"},{"_id":"jar_5ec9e503e3e1b8c951c7488677600f7b0b0bb823","cookies":[],"created":1567085270335,"modified":1567085270335,"name":"Default Jar","parentId":"wrk_b2cc40fce1ca4c6fa36186cebf570c60","_type":"cookie_jar"}]}